<?xml version="1.0" encoding="utf-8" standalone="no"?>
<!DOCTYPE phrases SYSTEM "entities.dtd">
<epp:phrases xmlns="http://www.w3.org/1999/xhtml" xmlns:epp="http://eprints.org/ep3/phrase" xmlns:epc="http://eprints.org/ep3/control">

<epp:phrase id="Plugin/Screen/ManageOrcid:orcid_info"><p>For more information about connecting to ORCID, <a href="/orcid_support_advance.html" target="_blank">click here</a>.</p></epp:phrase>

<!-- New Fields -->
<epp:phrase id="user_fieldname_orcid_name">orcid.org Name</epp:phrase>
<epp:phrase id="user_fieldname_orcid_token_expires">ORCID Token Expiry</epp:phrase>

<epp:phrase id="eprint_fieldname_creators_putcode">ORCID Put Code</epp:phrase>

<!-- Authenticate ORCID -->
<epp:phrase id="Plugin/Screen/AuthenticateOrcid:title"><img class="orcid-icon" src="/images/orcid_16x16.png"/>Create or Connect your ORCID iD</epp:phrase>

<epp:phrase id="Plugin/Screen/AuthenticateOrcid:created_orcid_link">Profile successfully linked to ORCID for user: <epc:pin name="name" /></epp:phrase>
<epp:phrase id="Plugin/Screen/AuthenticateOrcid:updated_orcid_link">Permissions successfully updated for user: <epc:pin name="name" /></epp:phrase>
<epp:phrase id="Plugin/Screen/AuthenticateOrcid:failed_creating_orcid_link">ORCID AUTHENTICATION ERROR<br />We have been unable to connect your <epc:phrase ref="archive_name" /> account with your ORCID account for the following reason: <br /><strong><epc:pin name="message" /></strong><br />Please contact <a href="mailto:{$config{ORCID_contact_email}}"><epc:print expr="$config{ORCID_contact_email}"/></a> for assistance.</epp:phrase>
<epp:phrase id="Plugin/Screen/AuthenticateOrcid:denied_creating_orcid_link">ORCID AUTHENTICATION DENIED<br />We have been unable to link your <epc:phrase ref="archive_name" /> account with your ORCID account as the request was denied with the following message: <br /><strong><epc:pin name="message" /></strong><br />Without this connection we are unable to link your ORCID id to your publications in <epc:phrase ref="archive_name" /> or automatically maintain your publication details here or in the ORCID system. You are strongly encouraged to authorise the link by completing the steps below.<br />If you are having problems making the connection please contact <a href="mailto:{$config{ORCID_contact_email}}"><epc:print expr="$config{ORCID_contact_email}"/></a></epp:phrase>

<!-- Import from ORCID -->
<epp:phrase id="Plugin/Screen/ImportFromOrcid:title">Import from orcid.org</epp:phrase>
<epp:phrase id="Plugin/Screen/ImportFromOrcid:user_header">Import from orcid.org for <epc:pin name="user_name" /></epp:phrase>
<epp:phrase id="Plugin/Screen/ImportFromOrcid:action:import:title">Import from orcid.org</epp:phrase>
<epp:phrase id="Plugin/Screen/ImportFromOrcid:import_help">Select ORCID works to import via their DOIs</epp:phrase>
<epp:phrase id="Plugin/Screen/ImportFromOrcid:orcid_import_work"><span class="import_label">Import from orcid.org: </span></epp:phrase>
<epp:phrase id="Plugin/Screen/ImportFromOrcid:orcid_import_via_doi"><span class="import_label">Import via DOI: </span></epp:phrase>
<epp:phrase id="Plugin/Screen/ImportFromOrcid:orcid_duplicate_record"><span class="import_warning">Duplicate record found: <epc:pin name="title" /></span></epp:phrase>
<epp:phrase id="Plugin/Screen/ImportFromOrcid:imported_works">Successfully imported <epc:pin name="count" /> works from orcid.org</epp:phrase>
<epp:phrase id="Plugin/Screen/ImportFromOrcid:review_permissions">ORCID PERMISSION DENIED<br />Before you can import records from orcid.org, you must give the repository permission to retrieve restricted details from your ORCID profile. Please change your permissions below.</epp:phrase>
<epp:phrase id="Plugin/Screen/ImportFromOrcid:user_permissions">ORCID Permission DENIED<br />The user <epc:pin name="user" /> has not given the repository permission to retrieve restricted details from their ORCID profile.</epp:phrase>
<epp:phrase id="Plugin/Screen/ImportFromOrcid:show_last_modified">Only show records last modified since: </epp:phrase>
<epp:phrase id="Plugin/Screen/ImportFromOrcid:filter">Filter</epp:phrase>
<epp:phrase id="Plugin/Screen/ImportFromOrcid:duplicates">Items that have already been imported are not shown by default.</epp:phrase>
<epp:phrase id="Plugin/Screen/ImportFromOrcid:show_hide_duplicates">Show/hide duplicates</epp:phrase>
<epp:phrase id="Plugin/Screen/ImportFromOrcid:select">Select/Unselect all</epp:phrase>
<epp:phrase id="Plugin/Screen/ImportFromOrcid:no_items">There are no works to be imported.</epp:phrase>

<!-- Export to ORCID -->
<epp:phrase id="Plugin/Screen/ExportToOrcid:title">Export to orcid.org</epp:phrase>
<epp:phrase id="Plugin/Screen/ExportToOrcid:user_header">Export to orcid.org for <epc:pin name="user_name" /></epp:phrase>
<epp:phrase id="Plugin/Screen/ExportToOrcid:action:export:title">Export to orcid.org</epp:phrase>
<epp:phrase id="Plugin/Screen/ExportToOrcid:export_help">Select records to export to your orcid.org profile</epp:phrase>
<epp:phrase id="Plugin/Screen/ExportToOrcid:exported_eprints">Successfully exported <epc:pin name="count_successful" />/<epc:pin name="count_all" /> eprint records to orcid.org</epp:phrase>
<epp:phrase id="Plugin/Screen/ExportToOrcid:updated_eprints">Successfully updated <epc:pin name="count_overwrite" />/<epc:pin name="count_all" /> eprint records to orcid.org</epp:phrase>
<epp:phrase id="Plugin/Screen/ExportToOrcid:failed_eprints">Sorry! <epc:pin name="count_failed" />/<epc:pin name="count_all" /> eprint records could not be exported or updated! Please contact your administrator.</epp:phrase>
<epp:phrase id="Plugin/Screen/ExportToOrcid:deleted_in_orcid">Successfully deleted <epc:pin name="count_successful" />/<epc:pin name="count_all" /> items at orcid.org</epp:phrase>
<epp:phrase id="Plugin/Screen/ExportToOrcid:deleted_in_orcid_failed"><epc:pin name="count_failed" />/<epc:pin name="count_all" /> items could not be deleted at orcid.org</epp:phrase>
<epp:phrase id="Plugin/Screen/ExportToOrcid:delete">Remove from orcid.org profile</epp:phrase>
<epp:phrase id="Plugin/Screen/ExportToOrcid:review_permissions">ORCID PERMISSION DENIED<br />Before you can export records to orcid.org, you must give the repository permission to create and update activities on your ORCID record. Please change your permissions below.</epp:phrase>
<epp:phrase id="Plugin/Screen/ExportToOrcid:user_permissions">ORCID Permission DENIED<br />The user <epc:pin name="user" /> has not given the repository permission to create and update activities on your ORCID record.</epp:phrase>
<epp:phrase id="Plugin/Screen/ExportToOrcid:show_last_modified">Only show records last modified since: </epp:phrase>
<epp:phrase id="Plugin/Screen/ExportToOrcid:filter">Filter</epp:phrase>
<epp:phrase id="Plugin/Screen/ExportToOrcid:duplicates">Items that have already been exported are not shown by default.</epp:phrase>
<epp:phrase id="Plugin/Screen/ExportToOrcid:show_hide_duplicates">Show/hide duplicates</epp:phrase>
<epp:phrase id="Plugin/Screen/ExportToOrcid:select">Select/Unselect all</epp:phrase>
<epp:phrase id="Plugin/Screen/ExportToOrcid:delete">Remove from orcid.org profile</epp:phrase>
<epp:phrase id="Plugin/Screen/ExportToOrcid:no_items">There are no works to be exported.</epp:phrase>

<!-- Manage ORCID -->
<epp:phrase id="Plugin/Screen/ManageOrcid:title"><img class="orcid-icon" src="/images/orcid_16x16.png"/>Manage ORCID Permissions</epp:phrase>
<epp:phrase id="Plugin/Screen/ManageOrcid:orcid/connect"><img class="orcid-icon" src="/images/orcid_16x16.png"/>Connect to ORCID</epp:phrase>
<epp:phrase id="Plugin/Screen/ManageOrcid:orcid_initial_connect">Before you can use your ORCID you must first either connect your <epc:phrase ref="archive_name" /> account to your ORCID record, or create an ORCID if you do not already have one.</epp:phrase>
<epp:phrase id="Plugin/Screen/ManageOrcid:user_header">ORCID details for <epc:pin name="user_name" /></epp:phrase>
<epp:phrase id="Plugin/Screen/ManageOrcid:granted_permissions">The permissions to access your ORCID record that you have granted to <epc:phrase ref="archive_name" /> via the ORCID system are listed here: </epp:phrase>
<epp:phrase id="Plugin/Screen/ManageOrcid:permission:/authenticate">Retrieve your ORCID id only</epp:phrase>
<epp:phrase id="Plugin/Screen/ManageOrcid:permission:/person/update">Create and update existing biographical (affiliation) details already added to your ORCID record by <epc:phrase ref="archive_name" /></epp:phrase>
<epp:phrase id="Plugin/Screen/ManageOrcid:permission:/activities/update">Create and update details of your research activities (publications, and education or employment) already added to your ORCID record by <epc:phrase ref="archive_name" /></epp:phrase>
<epp:phrase id="Plugin/Screen/ManageOrcid:permission:/read-limited">Retrieve details from your ORCID profile restricted to trusted parties only</epp:phrase>
<epp:phrase id="Plugin/Screen/ManageOrcid:permissions_instructions">These permissions are due to expire on <span class="expiry_date"><epc:pin name="expiry_date" /></span>.<br /><strong>Please Note:</strong> You can remove the granted permissions at any time from within your ORCID account or by changing the selected permissions below and re-connecting to ORCID.<br /><br />We will only use these granted permissions as indicated below. To change how we use these conditions please contact <a href="mailto:{$config{ORCID_contact_email}}"><epc:print expr="$config{ORCID_contact_email}"/></a><br /><br />Select the permissions you would like to grant to the repository below. Once selected, click the 'Create or Connect your ORCID iD' button to update your permissions.</epp:phrase>

<epp:phrase id="Plugin/Screen/ManageOrcid:/authenticate_select_text">Connect to ORCID</epp:phrase>
<epp:phrase id="Plugin/Screen/ManageOrcid:/authenticate_select_description">Allows <epc:phrase ref="archive_name" /> to link your ORCID id with your <epc:phrase ref="archive_name" /> record. This is the minimum permission required and is therefore uneditable</epp:phrase>
<epp:phrase id="Plugin/Screen/ManageOrcid:/activities/update_select_text">Create and update activities on your ORCID record</epp:phrase>
<epp:phrase id="Plugin/Screen/ManageOrcid:/activities/update_select_description">
Allows <epc:phrase ref="archive_name" /> to add details of your publications to your ORCID record and update the details of publications which have already been added to your ORCID record by <epc:phrase ref="archive_name" />.<br/><br/>
Upon allowing this permission, <epc:phrase ref="archive_name" /> will also attempt to update your employment or education acitivities. Please see <a href="/orcid_support_advance.html#updating-affiliation" target="_blank">Updating Employment/Education Activities</a> for more information.
</epp:phrase>
<epp:phrase id="Plugin/Screen/ManageOrcid:/person/update_select_text">Add and update affiliation details on your ORCID record</epp:phrase>
<epp:phrase id="Plugin/Screen/ManageOrcid:/person/update_select_description">Allows <epc:phrase ref="archive_name" /> to add information about your institutional affiliaton to your ORCID record and update your affiliation information which has already been added by <epc:phrase ref="archive_name" /></epp:phrase>
<epp:phrase id="Plugin/Screen/ManageOrcid:/read-limited_select_text">Retrieve restricted details from your ORCID profile</epp:phrase>
<epp:phrase id="Plugin/Screen/ManageOrcid:/read-limited_select_description">Allows <epc:phrase ref="archive_name" /> to retrieve details from your ORCID profile that are restricted to your trusted parties only</epp:phrase>
<epp:phrase id="Plugin/Screen/ManageOrcid:admin_local_user_perms_button">Update Local Permissions</epp:phrase>
<epp:phrase id="Plugin/Screen/ManageOrcid:admin_disconnect_button">Disconnect from ORCID</epp:phrase>
<epp:phrase id="Plugin/Screen/ManageOrcid:local_user_connect_orcid_button">Create or Connect your ORCID iD</epp:phrase>
<epp:phrase id="Plugin/Screen/ManageOrcid:disconnected">You are not currently connected to ORCID</epp:phrase>
<epp:phrase id="Plugin/Screen/ManageOrcid:confirm_erase_dialog">Are you sure?\nOnce removed we will not be able to maintain the user&apos;s ORCID record until they reauthenticate with ORCID</epp:phrase>

<!-- Name Report -->
<epp:phrase id="Plugin/Screen/Report/Orcid/CheckName:title">orcid.org Name Mismatch</epp:phrase>
<epp:phrase id="given_name_mismatch">Name does not match given name on orcid.org: <epc:pin name="given" /></epp:phrase>
<epp:phrase id="family_name_mismatch">Name does not match family name on orcid.org: <epc:pin name="family" /></epp:phrase>
<epp:phrase id="exportfields:check_name">User</epp:phrase>

<!-- UserPerms Report -->
<epp:phrase id="report/userperms:/authenticate">Retrieve your ORCID id granted</epp:phrase>
<epp:phrase id="report/userperms:/activities/update">Create and update details of your research activities granted</epp:phrase>
<epp:phrase id="report/userperms:/read-limited">Retrieve details from your ORCID profile restricted to trusted parties only granted</epp:phrase>

<!-- ORCID Field -->
<epp:phrase id="user_fieldhelp_orcid">Use 'Connect to ORCID' link to set your ORCID.</epp:phrase>

</epp:phrases>
